{"meta":{"name":"TELEMUNDO-VISIONUNIVERSO","id":"Ecuaplay38","type":"channel","posterShape":"landscape","videos":[{"id":"Ecuaplaystream_38_0","title":"USA | Telemundo San francisco"},{"id":"Ecuaplaystream_38_1","title":"USA | Telemundo Philadelphia"},{"id":"Ecuaplaystream_38_2","title":"USA | Telemundo New York"},{"id":"Ecuaplaystream_38_3","title":"USA | Telemundo Los Angeles"},{"id":"Ecuaplaystream_38_4","title":"USA | Telemundo Fresno"},{"id":"Ecuaplaystream_38_5","title":"USA | Telemundo Denver"},{"id":"Ecuaplaystream_38_6","title":"USA | Telemundo Dallas"},{"id":"Ecuaplaystream_38_7","title":"USA | Telemundo Chicago"},{"id":"Ecuaplaystream_38_8","title":"USA | Telemundo Boston"},{"id":"Ecuaplaystream_38_9","title":"USA | NBC Telemundo"},{"id":"Ecuaplaystream_38_10","title":"USA || TELEMUNDO MIAMI"},{"id":"Ecuaplaystream_38_11","title":"USA | TELEMUNDO Phoenix Arizona"},{"id":"Ecuaplaystream_38_12","title":"USA |  Telemundo Miami OPC 2"},{"id":"Ecuaplaystream_38_13","title":"USA | Univision Puerto Rico"},{"id":"Ecuaplaystream_38_14","title":"USA | Univision Miami"},{"id":"Ecuaplaystream_38_15","title":"USA |Usa Univision Atlanta"},{"id":"Ecuaplaystream_38_16","title":"USA |Usa Univision Austin"},{"id":"Ecuaplaystream_38_17","title":"USA |Usa Univision Cleveland"},{"id":"Ecuaplaystream_38_18","title":"USA |Usa Univision Fresno"},{"id":"Ecuaplaystream_38_19","title":"USA |Usa Univision Philadelphia"},{"id":"Ecuaplaystream_38_20","title":"USA |Usa Univision Phoenix"},{"id":"Ecuaplaystream_38_21","title":"USA |Usa Univision Raleigh"},{"id":"Ecuaplaystream_38_22","title":"USA |Usa Univision Salt Lake"},{"id":"Ecuaplaystream_38_23","title":"USA |Usa Univision San Antonio"},{"id":"Ecuaplaystream_38_24","title":"USA |Usa Univision San Francisco"},{"id":"Ecuaplaystream_38_25","title":"USA |Usa Univision Albuquerque Santa Fe"},{"id":"Ecuaplaystream_38_26","title":"USA |Usa Univision Chicago"},{"id":"Ecuaplaystream_38_27","title":"USA |Usa Univision DALLAS"},{"id":"Ecuaplaystream_38_28","title":"USA |Usa Univision EAST"},{"id":"Ecuaplaystream_38_29","title":"USA | VISION HOUSTON"},{"id":"Ecuaplaystream_38_30","title":"USA | VISION LA"},{"id":"Ecuaplaystream_38_31","title":"USA | VISION WEST"},{"id":"Ecuaplaystream_38_32","title":"USA | VISION NY1"},{"id":"Ecuaplaystream_38_33","title":"USA | VISION NY"}]}}